{
    "header": {
        "seq": 14661,
        "stamp": {
            "secs": 1681165372,
            "nsecs": 991278831
        },
        "frame_id": "atracsys"
    },
    "pose": {
        "position": {
            "x": 0.08254509735107422,
            "y": 0.13077691650390624,
            "z": 0.8967034301757812
        },
        "orientation": {
            "x": -0.5097773771414481,
            "y": 0.014797118975327556,
            "z": -0.005588301031958647,
            "w": 0.8601609395435206
        }
    }
}