{
    "header": {
        "seq": 36420,
        "stamp": {
            "secs": 1681165591,
            "nsecs": 929775473
        },
        "frame_id": "atracsys"
    },
    "pose": {
        "position": {
            "x": 0.08249199676513672,
            "y": 0.13088241577148438,
            "z": 0.8971390991210938
        },
        "orientation": {
            "x": -0.5110694341443569,
            "y": 0.014705305538490459,
            "z": -0.00596219456195996,
            "w": 0.8593929483701805
        }
    }
}