{
    "header": {
        "seq": 13126,
        "stamp": {
            "secs": 1681165357,
            "nsecs": 543409347
        },
        "frame_id": "atracsys"
    },
    "pose": {
        "position": {
            "x": 0.08254590606689453,
            "y": 0.13082595825195312,
            "z": 0.8966788330078125
        },
        "orientation": {
            "x": -0.5097657705483004,
            "y": 0.01474047938974675,
            "z": -0.005567800387846942,
            "w": 0.8601689235513564
        }
    }
}