{
    "header": {
        "seq": 35554,
        "stamp": {
            "secs": 1681165583,
            "nsecs": 216280711
        },
        "frame_id": "atracsys"
    },
    "pose": {
        "position": {
            "x": 0.08248358154296875,
            "y": 0.1308990936279297,
            "z": 0.8971953735351562
        },
        "orientation": {
            "x": -0.511043330284821,
            "y": 0.014696136643416942,
            "z": -0.005904997153568209,
            "w": 0.8594090231942959
        }
    }
}