{
    "header": {
        "seq": 4308,
        "stamp": {
            "secs": 1681165265,
            "nsecs": 142927305
        },
        "frame_id": "atracsys"
    },
    "pose": {
        "position": {
            "x": 0.29145404052734375,
            "y": 0.09812592315673828,
            "z": 0.8304501342773438
        },
        "orientation": {
            "x": -0.5005252437545609,
            "y": 0.07536893049676428,
            "z": 0.04384860424006436,
            "w": 0.8613195136454355
        }
    }
}