{
    "header": {
        "seq": 25963,
        "stamp": {
            "secs": 1681165486,
            "nsecs": 720260209
        },
        "frame_id": "atracsys"
    },
    "pose": {
        "position": {
            "x": 0.08251239776611329,
            "y": 0.1308147735595703,
            "z": 0.8968483276367187
        },
        "orientation": {
            "x": -0.5106188579801959,
            "y": 0.01497809773516009,
            "z": -0.005972552671913762,
            "w": 0.8596559585542449
        }
    }
}