{
    "header": {
        "seq": 1454,
        "stamp": {
            "secs": 1681165236,
            "nsecs": 429324596
        },
        "frame_id": "atracsys"
    },
    "pose": {
        "position": {
            "x": 0.2537083587646484,
            "y": 0.09534751129150391,
            "z": 0.83260498046875
        },
        "orientation": {
            "x": -0.49759207989103466,
            "y": 0.05429342814149636,
            "z": 0.028704314077756716,
            "w": 0.8652343081753543
        }
    }
}