{
    "header": {
        "seq": 4326,
        "stamp": {
            "secs": 1681165265,
            "nsecs": 325013531
        },
        "frame_id": "atracsys"
    },
    "pose": {
        "position": {
            "x": 0.2914540100097656,
            "y": 0.09812744903564453,
            "z": 0.8304569091796875
        },
        "orientation": {
            "x": -0.5005233837144739,
            "y": 0.07538807329614469,
            "z": 0.04385840971258271,
            "w": 0.8613184200150326
        }
    }
}