{
    "header": {
        "seq": 30892,
        "stamp": {
            "secs": 1681165536,
            "nsecs": 308602445
        },
        "frame_id": "atracsys"
    },
    "pose": {
        "position": {
            "x": 0.08250418090820312,
            "y": 0.13090594482421875,
            "z": 0.8970805053710937
        },
        "orientation": {
            "x": -0.5108900503116013,
            "y": 0.014888646949198857,
            "z": -0.0057892848839134195,
            "w": 0.8594976258635998
        }
    }
}