{
    "header": {
        "seq": 26158,
        "stamp": {
            "secs": 1675626191,
            "nsecs": 421990768
        },
        "frame_id": "atracsys"
    },
    "pose": {
        "position": {
            "x": 0.15138401794433595,
            "y": -0.04786447525024414,
            "z": 0.7742028198242188
        },
        "orientation": {
            "x": -0.019453158364442377,
            "y": -0.3074240361557577,
            "z": 0.8743343866751928,
            "w": 0.37503522088020697
        }
    }
}