{
    "header": {
        "seq": 11133,
        "stamp": {
            "secs": 1675626040,
            "nsecs": 176457461
        },
        "frame_id": "atracsys"
    },
    "pose": {
        "position": {
            "x": 0.12088443756103516,
            "y": -0.08672053527832031,
            "z": 0.8471447143554688
        },
        "orientation": {
            "x": -0.1331007901014861,
            "y": -0.20838638587994207,
            "z": 0.868174527649463,
            "w": 0.4302700121957001
        }
    }
}