{
    "header": {
        "seq": 25520,
        "stamp": {
            "secs": 1675626185,
            "nsecs": 4053254
        },
        "frame_id": "atracsys"
    },
    "pose": {
        "position": {
            "x": 0.15641966247558595,
            "y": -0.04831658935546875,
            "z": 0.7760506591796875
        },
        "orientation": {
            "x": -0.017931957367996958,
            "y": -0.2975615047937256,
            "z": 0.8790299556921174,
            "w": 0.37207785847287406
        }
    }
}