{
    "header": {
        "seq": 33439,
        "stamp": {
            "secs": 1678823414,
            "nsecs": 766342281
        },
        "frame_id": "atracsys"
    },
    "pose": {
        "position": {
            "x": 0.6268565673828125,
            "y": -0.005565253257751465,
            "z": 0.29190438842773436
        },
        "orientation": {
            "x": -0.006516314335260942,
            "y": -0.5203224353801561,
            "z": -0.09444888712437476,
            "w": 0.8487057844792355
        }
    }
}