{
    "header": {
        "seq": 33757,
        "stamp": {
            "secs": 1678823417,
            "nsecs": 972323710
        },
        "frame_id": "atracsys"
    },
    "pose": {
        "position": {
            "x": 0.6268253784179688,
            "y": -0.005374573707580567,
            "z": 0.291846435546875
        },
        "orientation": {
            "x": -0.006410613047817843,
            "y": -0.5202764634556626,
            "z": -0.09443434658526872,
            "w": 0.8487363900525494
        }
    }
}