{
    "header": {
        "seq": 34520,
        "stamp": {
            "secs": 1678823425,
            "nsecs": 652898379
        },
        "frame_id": "atracsys"
    },
    "pose": {
        "position": {
            "x": 0.62682470703125,
            "y": -0.005442598819732666,
            "z": 0.29186962890625
        },
        "orientation": {
            "x": -0.0064405003673936485,
            "y": -0.5202869134720192,
            "z": -0.09445653882905733,
            "w": 0.8487272882953699
        }
    }
}