{
    "header": {
        "seq": 23363,
        "stamp": {
            "secs": 1678823313,
            "nsecs": 241310614
        },
        "frame_id": "atracsys"
    },
    "pose": {
        "position": {
            "x": 0.6270263061523438,
            "y": -0.005548795700073242,
            "z": 0.29215298461914063
        },
        "orientation": {
            "x": -0.0065535558316912575,
            "y": -0.520370790542153,
            "z": -0.09425102169082718,
            "w": 0.8486978473913616
        }
    }
}