{
    "header": {
        "seq": 34805,
        "stamp": {
            "secs": 1678823428,
            "nsecs": 521528893
        },
        "frame_id": "atracsys"
    },
    "pose": {
        "position": {
            "x": 0.6269044189453125,
            "y": -0.005259270668029785,
            "z": 0.2918605041503906
        },
        "orientation": {
            "x": -0.006332564840302431,
            "y": -0.5203166880656118,
            "z": -0.09443317019917745,
            "w": 0.8487124478344296
        }
    }
}