{
    "header": {
        "seq": 40918,
        "stamp": {
            "secs": 1666021903,
            "nsecs": 801946243
        },
        "frame_id": "atracsys"
    },
    "pose": {
        "position": {
            "x": 0.057690193176269534,
            "y": 0.05806857299804687,
            "z": 1.16931396484375
        },
        "orientation": {
            "x": 0.016911400587280863,
            "y": 0.2646449389006034,
            "z": 0.0259525543763887,
            "w": 0.9638482898080034
        }
    }
}