{
    "header": {
        "seq": 34927,
        "stamp": {
            "secs": 1666021843,
            "nsecs": 464408391
        },
        "frame_id": "atracsys"
    },
    "pose": {
        "position": {
            "x": 0.05762785339355469,
            "y": 0.05808396148681641,
            "z": 1.1693172607421876
        },
        "orientation": {
            "x": 0.01675963421525871,
            "y": 0.26433159280175056,
            "z": 0.02582690029286986,
            "w": 0.9639402963509319
        }
    }
}