{
    "header": {
        "seq": 33289,
        "stamp": {
            "secs": 1681165593,
            "nsecs": 852263385
        },
        "frame_id": "atracsys"
    },
    "pose": {
        "position": {
            "x": 0.1077397232055664,
            "y": -0.022867015838623047,
            "z": 0.9640838623046876
        },
        "orientation": {
            "x": -0.1369339655588268,
            "y": 0.18276554847883636,
            "z": 0.9689100604282225,
            "w": 0.09517950497109462
        }
    }
}