{
    "header": {
        "seq": 34421,
        "stamp": {
            "secs": 1681165605,
            "nsecs": 246261095
        },
        "frame_id": "atracsys"
    },
    "pose": {
        "position": {
            "x": 0.09710076904296876,
            "y": 0.018413164138793944,
            "z": 1.0188013305664063
        },
        "orientation": {
            "x": -0.15717620504379295,
            "y": 0.23904367057996095,
            "z": 0.9581751474504651,
            "w": 0.00735873168217597
        }
    }
}