{
    "header": {
        "seq": 11546,
        "stamp": {
            "secs": 1681165375,
            "nsecs": 18301116
        },
        "frame_id": "atracsys"
    },
    "pose": {
        "position": {
            "x": 0.20987860107421877,
            "y": 0.004900197982788086,
            "z": 0.9748310546875
        },
        "orientation": {
            "x": -0.2039221807772179,
            "y": 0.02466268170069619,
            "z": 0.9648229810956757,
            "w": -0.16408568331224838
        }
    }
}