{
    "header": {
        "seq": 26825,
        "stamp": {
            "secs": 1681165528,
            "nsecs": 819000567
        },
        "frame_id": "atracsys"
    },
    "pose": {
        "position": {
            "x": 0.16543804931640627,
            "y": -0.014416868209838868,
            "z": 0.9653511962890625
        },
        "orientation": {
            "x": -0.17858845156759712,
            "y": 0.15560002226889202,
            "z": 0.9715089814626521,
            "w": 0.008068269579577557
        }
    }
}