{
    "header": {
        "seq": 994,
        "stamp": {
            "secs": 1681165231,
            "nsecs": 799418815
        },
        "frame_id": "atracsys"
    },
    "pose": {
        "position": {
            "x": 0.2717098388671875,
            "y": -0.053476272583007814,
            "z": 0.8980372314453126
        },
        "orientation": {
            "x": -0.06617643125409499,
            "y": 0.23086918275413745,
            "z": 0.9690736627610296,
            "w": 0.05671275468385454
        }
    }
}