{
    "header": {
        "seq": 20022,
        "stamp": {
            "secs": 1677532000,
            "nsecs": 296066480
        },
        "frame_id": "atracsys"
    },
    "pose": {
        "position": {
            "x": 0.19654107666015624,
            "y": 0.19013027954101563,
            "z": 1.03921435546875
        },
        "orientation": {
            "x": -0.01562443781253208,
            "y": 0.08713908135476167,
            "z": -0.026855884270523003,
            "w": 0.9957115139053775
        }
    }
}