{
    "header": {
        "seq": 15370,
        "stamp": {
            "secs": 1677531953,
            "nsecs": 463247476
        },
        "frame_id": "atracsys"
    },
    "pose": {
        "position": {
            "x": 0.1965738525390625,
            "y": 0.19011305236816406,
            "z": 1.03921142578125
        },
        "orientation": {
            "x": -0.015763007076544978,
            "y": 0.08711909555016589,
            "z": -0.026857648028164344,
            "w": 0.9957110311434846
        }
    }
}