{
    "header": {
        "seq": 16066,
        "stamp": {
            "secs": 1677532007,
            "nsecs": 146813519
        },
        "frame_id": "atracsys"
    },
    "pose": {
        "position": {
            "x": 0.7353427124023437,
            "y": 0.2278221893310547,
            "z": 0.546611328125
        },
        "orientation": {
            "x": 0.3282984060446215,
            "y": -0.4970589912282085,
            "z": -0.06909955846748032,
            "w": 0.800236069449107
        }
    }
}