{
    "header": {
        "seq": 8725,
        "stamp": {
            "secs": 1678823172,
            "nsecs": 131036052
        },
        "frame_id": "atracsys"
    },
    "pose": {
        "position": {
            "x": 0.5666966552734375,
            "y": -0.0454990119934082,
            "z": 0.3656495361328125
        },
        "orientation": {
            "x": 0.11452626816702997,
            "y": -0.41782302728877957,
            "z": -0.1391170832054072,
            "w": 0.8904796959658279
        }
    }
}