{
    "header": {
        "seq": 31085,
        "stamp": {
            "secs": 1678823399,
            "nsecs": 351508903
        },
        "frame_id": "atracsys"
    },
    "pose": {
        "position": {
            "x": 0.324938720703125,
            "y": 0.060511932373046876,
            "z": 0.261970703125
        },
        "orientation": {
            "x": 0.1680611186860067,
            "y": -0.2624734977239896,
            "z": -0.10219022203203205,
            "w": 0.9446799891495462
        }
    }
}