{
    "header": {
        "seq": 38771,
        "stamp": {
            "secs": 1678823476,
            "nsecs": 808019601
        },
        "frame_id": "atracsys"
    },
    "pose": {
        "position": {
            "x": 0.16357421875,
            "y": -0.10101728820800782,
            "z": 0.23078785705566407
        },
        "orientation": {
            "x": 0.06536516171765058,
            "y": -0.11443456568748467,
            "z": 0.10292050087279463,
            "w": 0.9859206338796422
        }
    }
}