{
    "header": {
        "seq": 23776,
        "stamp": {
            "secs": 1678823325,
            "nsecs": 677153767
        },
        "frame_id": "atracsys"
    },
    "pose": {
        "position": {
            "x": 0.2722715759277344,
            "y": 0.21902851867675782,
            "z": 0.1955416259765625
        },
        "orientation": {
            "x": 0.2680460456747932,
            "y": -0.19998872070643603,
            "z": -0.015516201444438608,
            "w": 0.9422924580410508
        }
    }
}