{
    "header": {
        "seq": 27704,
        "stamp": {
            "secs": 1681248037,
            "nsecs": 279126330
        },
        "frame_id": "atracsys"
    },
    "pose": {
        "position": {
            "x": 0.22192051696777343,
            "y": 0.004971714496612549,
            "z": 1.0710076904296875
        },
        "orientation": {
            "x": 0.9639757813513649,
            "y": 0.0984636822367977,
            "z": -0.16468653177962775,
            "w": 0.18421167850816123
        }
    }
}