{
    "header": {
        "seq": 31476,
        "stamp": {
            "secs": 1681248075,
            "nsecs": 216389124
        },
        "frame_id": "atracsys"
    },
    "pose": {
        "position": {
            "x": 0.1956031494140625,
            "y": 0.0040372729301452635,
            "z": 1.061508544921875
        },
        "orientation": {
            "x": 0.9757890325575872,
            "y": 0.1438056485579937,
            "z": -0.14341292723096924,
            "w": 0.08116915477068641
        }
    }
}