{
    "header": {
        "seq": 12647,
        "stamp": {
            "secs": 1681247885,
            "nsecs": 759923127
        },
        "frame_id": "atracsys"
    },
    "pose": {
        "position": {
            "x": 0.14095358276367187,
            "y": 0.016580717086791992,
            "z": 1.105942626953125
        },
        "orientation": {
            "x": 0.9006835044944217,
            "y": -0.030307638228544945,
            "z": -0.3785108677023967,
            "w": 0.2111402255086267
        }
    }
}