{
    "header": {
        "seq": 26811,
        "stamp": {
            "secs": 1681248028,
            "nsecs": 297004436
        },
        "frame_id": "atracsys"
    },
    "pose": {
        "position": {
            "x": 0.2587442321777344,
            "y": 0.021161495208740236,
            "z": 1.0741412353515625
        },
        "orientation": {
            "x": 0.9555948201164104,
            "y": 0.1801967153893962,
            "z": -0.1071839781851374,
            "w": 0.20707312319556676
        }
    }
}