{
    "header": {
        "seq": 10387,
        "stamp": {
            "secs": 1681247863,
            "nsecs": 13618271
        },
        "frame_id": "atracsys"
    },
    "pose": {
        "position": {
            "x": 0.19009605407714844,
            "y": 0.023579753875732423,
            "z": 1.1082232666015626
        },
        "orientation": {
            "x": 0.9305222427268547,
            "y": 0.06541963456555201,
            "z": -0.30891715009008996,
            "w": 0.18552310256167798
        }
    }
}