{
    "header": {
        "seq": 36386,
        "stamp": {
            "secs": 1675626233,
            "nsecs": 553610306
        },
        "frame_id": "atracsys"
    },
    "pose": {
        "position": {
            "x": 0.26526251220703123,
            "y": 0.13622059631347658,
            "z": 0.8952788696289062
        },
        "orientation": {
            "x": 0.013291825253433833,
            "y": 0.03996618162686033,
            "z": -0.030299646418593996,
            "w": 0.9986530744630536
        }
    }
}