{
    "header": {
        "seq": 37061,
        "stamp": {
            "secs": 1675626240,
            "nsecs": 341582715
        },
        "frame_id": "atracsys"
    },
    "pose": {
        "position": {
            "x": 0.2652433776855469,
            "y": 0.13623936462402345,
            "z": 0.8952826538085937
        },
        "orientation": {
            "x": 0.013308255756709358,
            "y": 0.03998052351918522,
            "z": -0.030371788658485412,
            "w": 0.9986500901324398
        }
    }
}