{
    "header": {
        "seq": 39297,
        "stamp": {
            "secs": 1675626262,
            "nsecs": 825310018
        },
        "frame_id": "atracsys"
    },
    "pose": {
        "position": {
            "x": 0.2652392272949219,
            "y": 0.13624964904785156,
            "z": 0.89528369140625
        },
        "orientation": {
            "x": 0.013274564473204893,
            "y": 0.039973229947917764,
            "z": -0.030371247805922406,
            "w": 0.9986508469591807
        }
    }
}