{
    "header": {
        "seq": 35065,
        "stamp": {
            "secs": 1677532151,
            "nsecs": 771135360
        },
        "frame_id": "atracsys"
    },
    "pose": {
        "position": {
            "x": 0.1965357360839844,
            "y": 0.19011087036132812,
            "z": 1.0392298583984376
        },
        "orientation": {
            "x": -0.015809343588625235,
            "y": 0.08711712324664246,
            "z": -0.026890785773120564,
            "w": 0.9957095746918527
        }
    }
}