{
    "header": {
        "seq": 31633,
        "stamp": {
            "secs": 1677532117,
            "nsecs": 209859548
        },
        "frame_id": "atracsys"
    },
    "pose": {
        "position": {
            "x": 0.19653045654296875,
            "y": 0.19010591125488283,
            "z": 1.039208984375
        },
        "orientation": {
            "x": -0.015697187319913753,
            "y": 0.08711531482075055,
            "z": -0.02689010109900855,
            "w": 0.995711525843108
        }
    }
}