{
    "header": {
        "seq": 25978,
        "stamp": {
            "secs": 1677532106,
            "nsecs": 967980975
        },
        "frame_id": "atracsys"
    },
    "pose": {
        "position": {
            "x": 0.7839536743164063,
            "y": 0.25058251953125,
            "z": 0.65419873046875
        },
        "orientation": {
            "x": 0.3713490903839359,
            "y": -0.529549823869126,
            "z": -0.10210934259998694,
            "w": 0.7558111664066626
        }
    }
}