{
    "header": {
        "seq": 12756,
        "stamp": {
            "secs": 1681247878,
            "nsecs": 500165112
        },
        "frame_id": "atracsys"
    },
    "pose": {
        "position": {
            "x": 0.18212274169921874,
            "y": 0.16659829711914062,
            "z": 0.933849853515625
        },
        "orientation": {
            "x": 0.8251757392310619,
            "y": -0.13297303053043028,
            "z": 0.2260932135504174,
            "w": 0.5002849501258949
        }
    }
}