{
    "header": {
        "seq": 24858,
        "stamp": {
            "secs": 1681248000,
            "nsecs": 270284424
        },
        "frame_id": "atracsys"
    },
    "pose": {
        "position": {
            "x": 0.18210870361328124,
            "y": 0.16661814880371095,
            "z": 0.9339309692382812
        },
        "orientation": {
            "x": 0.8251188425854495,
            "y": -0.1329467580519354,
            "z": 0.2261602588483067,
            "w": 0.5003554660954501
        }
    }
}