{
    "header": {
        "seq": 28313,
        "stamp": {
            "secs": 1681248035,
            "nsecs": 40330700
        },
        "frame_id": "atracsys"
    },
    "pose": {
        "position": {
            "x": 0.18211141967773437,
            "y": 0.1666028289794922,
            "z": 0.9339326171875
        },
        "orientation": {
            "x": 0.8251666546365835,
            "y": -0.13292983502653477,
            "z": 0.22609379232511698,
            "w": 0.500311151292608
        }
    }
}