{
    "header": {
        "stamp": {
            "secs": 1650921881, 
            "nsecs": 750504669
        }, 
        "frame_id": "atracsys", 
        "seq": 145712
    }, 
    "pose": {
        "position": {
            "y": -0.0326082229614, 
            "x": -0.213494995117, 
            "z": 1.17791357422
        }, 
        "orientation": {
            "y": 0.0792083350995, 
            "x": 0.0189899102379, 
            "z": 0.334197605728, 
            "w": 0.938976774625
        }
    }
}